briton/__init__.py
briton/async_util.py
briton/backend/__init__.py
briton/backend/backend_types.py
briton/backend/briton_request.py
briton/backend/default_backend.py
briton/backend/legacy_backend.py
briton/backend/utils.py
briton/briton.py
briton/config_utils.py
briton/constants.py
briton/data_structures.py
briton/error_handling.py
briton/errors.py
briton/flags.py
briton/fs.py
briton/hf_utils.py
briton/input_utils.py
briton/lora_cache.py
briton/network.py
briton/openai.py
briton/proc_utils.py
briton/proto/__init__.py
briton/proto/briton_pb2.py
briton/proto/briton_pb2.pyi
briton/proto/briton_pb2_grpc.py
briton/rand_util.py
briton/request_id_generator.py
briton/schema.py
briton/secrets.py
briton/spec_dec.py
briton/spec_dec_truss_model.py
briton/tool_parsers/__init__.py
briton/tool_parsers/abstract_tool_parser.py
briton/tool_parsers/hermes_tool_parser.py
briton/tool_parsers/llama_tool_parser.py
briton/tool_parsers/mistral_tool_parser.py
briton/tool_parsers/utils.py
briton/trtllm_config.py
briton/truss_model.py
briton/truss_monitor.py
briton-0.5.0.dist-info/METADATA
briton-0.5.0.dist-info/WHEEL
briton-0.5.0.dist-info/entry_points.txt
briton-0.5.0.dist-info/RECORD
