Metadata-Version: 2.3
Name: briton
Version: 0.5.0
Summary: Python component of using Briton
License: MIT
Author: Pankaj Gupta
Author-email: pankaj@baseten.co
Requires-Python: >=3.10,<3.13
Classifier: License :: OSI Approved :: MIT License
Classifier: Programming Language :: Python :: 3
Classifier: Programming Language :: Python :: 3.10
Classifier: Programming Language :: Python :: 3.11
Classifier: Programming Language :: Python :: 3.12
Requires-Dist: datasets (>=3.4.1,<4.0.0)
Requires-Dist: fastapi (>=0.114.0,<0.115.0)
Requires-Dist: grpcio (>=1.62.3,<2.0.0)
Requires-Dist: grpcio-tools (>=1.62.3,<2.0.0)
Requires-Dist: hf-transfer (>=0.1.8,<0.2.0)
Requires-Dist: huggingface-hub (>=0.25.2,<0.26.0)
Requires-Dist: jinja2 (>=3.1.6,<4.0.0)
Requires-Dist: openai (>=1.51.2,<2.0.0)
Requires-Dist: partial-json-parser (>=0.2.1.1.post5,<0.3.0.0)
Requires-Dist: psutil (==5.9.4)
Requires-Dist: pydantic (>=2.9.2,<3.0.0)
Requires-Dist: sentencepiece (>=0.2.0,<0.3.0)
Requires-Dist: transformers (==4.45.1)
